glean/__init__.py
glean/_builtins.py
glean/_ffi.py
glean/_loader.py
glean/_process_dispatcher.py
glean/_subprocess/__init__.py
glean/_subprocess/_process_dispatcher_helper.py
glean/_uniffi/__init__.py
glean/_uniffi/glean.py
glean/_uniffi/glean_ffi.dll
glean/_util.py
glean/config.py
glean/glean.py
glean/metrics/__init__.py
glean/metrics/datetime.py
glean/metrics/event.py
glean/metrics/labeled.py
glean/metrics/object.py
glean/metrics/ping.py
glean/metrics/string.py
glean/metrics/timespan.py
glean/metrics/timing_distribution.py
glean/metrics/url.py
glean/metrics/uuid.py
glean/metrics.yaml
glean/net/__init__.py
glean/net/base_uploader.py
glean/net/http_client.py
glean/net/ping_upload_worker.py
glean/net/ping_uploader.py
glean/pings.yaml
glean/testing/__init__.py
glean_sdk-67.0.0.dist-info/METADATA
glean_sdk-67.0.0.dist-info/WHEEL
glean_sdk-67.0.0.dist-info/licenses/LICENSE
glean_sdk-67.0.0.dist-info/RECORD
