Metadata-Version: 2.4
Name: glean-sdk
Version: 67.0.0
Classifier: Intended Audience :: Developers
Classifier: Natural Language :: English
Classifier: Programming Language :: Rust
Classifier: Programming Language :: Python :: Implementation :: CPython
Classifier: Programming Language :: Python :: 3
Requires-Dist: semver>=2.13.0
Requires-Dist: glean-parser~=18.2
License-File: LICENSE
Summary: Mozilla's Glean Telemetry SDK: The Machine that Goes 'Ping!'
Maintainer-email: The Glean Team <glean-team@mozilla.com>
Requires-Python: >=3.9
Project-URL: changelog, https://mozilla.github.io/glean/book/appendix/changelog/sdk.html
Project-URL: homepage, https://mozilla.github.io/glean/
Project-URL: repository, https://github.com/mozilla/glean
